Metadata-Version: 1.0
Name: django-postgresql-function
Version: 0.1.0
Summary: Additional PostgreSQL DataBase Django functions
Home-page: https://github.com/maksimyuk/django-postgresql-function
Author: wgh
Author-email: maksimyuk.georgiy@gmail.com
License: MIT
Platform: UNKNOWN
